datetime_tools/bisect_year.py
datetime_tools/generate_days.py
datetime_tools/get_duration.py
datetime_tools/get_end_date.py
datetime_tools/get_tz.py
datetime_tools/get_year_and_week.py
datetime_tools/lookup.py
datetime_convertion_tools-0.0.15.dist-info/LICENSE
datetime_convertion_tools-0.0.15.dist-info/METADATA
datetime_convertion_tools-0.0.15.dist-info/WHEEL
datetime_convertion_tools-0.0.15.dist-info/RECORD
