Metadata-Version: 2.1
Name: datetime-convertion-tools
Version: 0.0.15
Summary: Common datetime operations
Author: Gustav Rasmussen
Requires-Python: >=3.11,<4.0
Classifier: Programming Language :: Python :: 3
Classifier: Programming Language :: Python :: 3.11
Classifier: Programming Language :: Python :: 3.12
Classifier: Programming Language :: Python :: 3.13
Requires-Dist: numpy (==2.2.0)
Requires-Dist: pandas (>=2.2.3,<3.0.0)
Requires-Dist: pytest-cov (>=6.0.0,<7.0.0)
Requires-Dist: ruff (>=0.8.4,<0.9.0)
